[{
    "id": "ACCT151",
    "view": {
      "x": 42,
      "y": 0
    }
  },
  {
    "id": "ACCT152",
    "view": {
      "x": 42,
      "y": 20
    }
  },
  {
    "id": "BUS003",
    "view": {
      "x": 10,
      "y": 0
    }
  },
  {
    "id": "BUS203",
    "view": {
      "x": 10,
      "y": 20
    }
  },
  {
    "id": "ECO001",
    "view": {
      "x": 34,
      "y": 0
    }
  },
  {
    "id": "BUS001",
    "view": {
      "x": 2,
      "y": 0
    }
  },
  {
    "id": "ENGL001",
    "view": {
      "x": 90,
      "y": 0
    }
  },
  {
    "id": "CSE001",
    "view": {
      "x": 82,
      "y": 0
    }
  },
  {
    "id": "CSE002",
    "view": {
      "x": 74,
      "y": 0
    }
  },
  {
    "id": "CSE017",
    "view": {
      "x": 74,
      "y": 20
    }
  },
  {
    "id": "CSE109",
    "view": {
      "x": 74,
      "y": 40
    }
  },
  {
    "id": "CSE202",
    "view": {
      "x": 82,
      "y": 40
    }
  },
  {
    "id": "CSE303",
    "view": {
      "x": 74,
      "y": 60
    }
  },
  {
    "id": "CSE262",
    "view": {
      "x": 90,
      "y": 40
    }
  },
  {
    "id": "CSE216",
    "view": {
      "x": 66,
      "y": 40
    }
  },
  {
    "id": "CSE241",
    "view": {
      "x": 58,
      "y": 40
    }
  },
  {
    "id": "MKT111",
    "view": {
      "x": 18,
      "y": 20
    }
  },
  {
    "id": "LAW201",
    "view": {
      "x": 26,
      "y": 20
    }
  },
  {
    "id": "ECO146",
    "view": {
      "x": 34,
      "y": 20
    }
  }
]